{
    "name": "White Castle Automa",
    "setup": [
        "2인 규칙에 맞춰서 세팅한다. (주사위 색깔별로 3개씩)",
        "원형 토큰 14개와 건물(모두 B면) 12개를 개인판 옆에 둔다.",
        "샘의 목장 주인 말과 기차 말을 시작 지점에 놓는다.",
        "샘은 시작 소 카드를 사용하지 않는다.",
        "시작 목표 타일을 1장 받고 개인판 옆에 뒷면으로 둔다.",
        "플레이어가 먼저 시작(6달러 1교환토큰, 핸드 4장)"
    ],
    "difficulties": [
        {
            "label": "easy",
            "description": [
                "가문 명성 점수 0점",
                "백로 마커 두 번째 칸",
                "시간 트랙 0칸 전진"
            ]
        },
        {
            "label": "medium",
            "description": [
                "가문 명성 점수 3점",
                "백로 마커 첫 번째 칸",
                "시간 트랙 1칸 전진"
            ]
        },
        {
            "label": "hard",
            "description": [
                "가문 명성 점수 8점",
                "백로 마커 두 번째 칸",
                "시간 트랙 3칸 전진"
            ]
        }
    ],
    "description": [
      "한장을 뽑아 더미 오른쪽에 앞면으로 놓는다.",
      "뒷면에 나온 주사위가 존재하면 주사위 이동 액션 진행한다.",
      "없으면 이전에 뽑은 카드 오른쪽에 앞면으로 놓고 계속 확인 주사위가 존재할떄까지 반복한다",
      "주사위 놓을 때 동전은 받지만 지불하지 않는다.",
      "주사위를 놓으려는 칸에 이미 놓여져 있으면 우물에 놓고 차이만큼 동전을 받는다.",
      "마지막으로 공개된 2장의 왼쪽 위부터 왼쪽 위, 왼쪽 아래, 오른쪽 위, 오른쪽 아래 순서로 진행한다.",
      "수행할 수 없는 행동이 있다면 현재 라운드 수만큼 가문명성 점수를 얻는다.",
      "모두 수행 후 뽑아둔 카드를 모두 더미 아래에 넣는다."
    ],
    "round_actions": [
      "기본 규칙 대로 차례 순서 조정",
      "오토마가 앞선다면 오토마의 동전 3개당 1점 * 라운드 수만큼 점수 획득 후 동전을 버린다.",
      "오토마가 뒤쳐진다면 오토마의 동전 5개당 1점 * 라운드 수만큼 점수 획득 후 동전을 버린다.",
      "1, 2라운드 종료 후 정원 단계에 해당하는 정원사가 있으면 그 정원사 말마다 현재 라운드 수만큼 점수를 얻는다.",
      "오토마 카드를 섞는다."
    ],
    "cards": [
        {
            "id": 1,
            "back_description": [
              "흰 주사위 다리 가운데",
              "히메지성 2층 오른쪽 칸"
            ],
            "description": [
                "모든 정원 카드 중 점수가 가장 작고 오토마가 놓여있지 않은 카드에 정원사를 놓는다. (여러 장이라면 원하는 칸)",
                "시간 트랙 1칸 전진, 가문 명성 점수 2점"
            ]
        },
        {
            "id": 2,
            "back_description": [
              "흰 주사위 다리 오른쪽",
              "히메지성과 훈련장 액션칸"
            ],
            "description": [
                "정문에 가신을 놓는다.",
                "가장 낮은 위치에 있는 가신 1칸 전진 (원하는 방에 놓고 카드를 제거한다. 3층이라면 다이묘 카드 맨 왼쪽 빈칸에 놓는다.)"
            ]
        },
        {
            "id": 3,
            "back_description": [
              "빨간 주사위 다리 오른쪽",
              "정원과 히메지성 액션칸"
            ],
            "description": [
                "정문에 가신을 놓는다.",
                "시간 트랙 2칸 전진, 동전 1개"
            ]
        },
        {
            "id": 4,
            "back_description": [
              "검은 주사위 다리 왼쪽",
              "히메지성과 훈련장 액션칸"
            ],
            "description": [
                "비용이 1인 훈련장에 무사를 놓는다.",
                "가장 낮은 위치에 있는 가신 2칸 전진 (원하는 방에 놓고 카드를 제거한다. 3층이라면 다이묘 카드 맨 왼쪽 빈칸에 놓는다.)"
            ]
        },
        {
            "id": 5,
            "back_description": [
              "검은 주사위 다리 가운데",
              "히메지성 2층 왼쪽 칸"
            ],
            "description": [
                "정문에 가신을 놓는다.",
                "시간 트랙 1칸 전진, 동전 3개"
            ]
        },
        {
            "id": 6,
            "back_description": [
              "검은 주사위 다리 오른쪽",
              "히메지성 1층 오른쪽 칸"
            ],
            "description": [
                "식물 정원 카드 중 점수가 가장 작고 오토마가 놓여있지 않은 카드에 정원사를 놓는다. (여러 장이라면 원하는 칸)",
                "동전 5개"
            ]
        },
        {
            "id": 7,
            "back_description": [
              "빨간 주사위 다리 가운데",
              "히메지성 1층 가운데 칸"
            ],
            "description": [
                "수석 정원 카드 중 점수가 가장 작고 오토마가 놓여있지 않은 카드에 정원사를 놓는다. (여러 장이라면 원하는 칸)",
                "가장 낮은 위치에 있는 가신 1칸 전진 (원하는 방에 놓고 카드를 제거한다. 3층이라면 다이묘 카드 맨 왼쪽 빈칸에 놓는다.)"
            ]
        },
        {
            "id": 8,
            "back_description": [
              "빨간 주사위 다리 왼쪽",
              "정원과 히메지성 액션칸"
            ],
            "description": [
                "비용이 5인 훈련장에 무사를 놓는다.",
                "시간 트랙 2칸 전진, 가문 명성 점수 1점"
            ]
        },
        {
            "id": 9,
            "back_description": [
              "흰색 주사위 다리 왼쪽",
              "히메지성 1층 왼쪽 칸"
            ],
            "description": [
                "비용이 3인 훈련장에 무사를 놓는다.",
                "가장 낮은 위치에 있는 가신 1칸 전진 (원하는 방에 놓고 카드를 제거한다. 3층이라면 다이묘 카드 맨 왼쪽 빈칸에 놓는다.)"
            ]
        }
    ]
}
